MANIFEST.in
README.md
setup.py
readabilipy/__init__.py
readabilipy/__main__.py
readabilipy/__version__.py
readabilipy/simple_json.py
readabilipy/simple_tree.py
readabilipy/utils.py
readabilipy.egg-info/PKG-INFO
readabilipy.egg-info/SOURCES.txt
readabilipy.egg-info/dependency_links.txt
readabilipy.egg-info/entry_points.txt
readabilipy.egg-info/requires.txt
readabilipy.egg-info/top_level.txt
readabilipy/extractors/__init__.py
readabilipy/extractors/extract_date.py
readabilipy/extractors/extract_element.py
readabilipy/extractors/extract_title.py
readabilipy/javascript/ExtractArticle.js
readabilipy/javascript/Readability.js
readabilipy/javascript/package.json
readabilipy/simplifiers/__init__.py
readabilipy/simplifiers/html.py
readabilipy/simplifiers/text.py