Metadata-Version: 2.1
Name: readabilipy
Version: 0.2.0
Summary: Python wrapper for Mozilla's Readability.js
Home-page: https://github.com/alan-turing-institute/ReadabiliPy
Author: The Alan Turing Institute
Author-email: info@turing.ac.uk
Maintainer: James Robinson
Maintainer-email: jrobinson@turing.ac.uk
License: MIT
Platform: UNKNOWN
Classifier: License :: OSI Approved :: MIT License
Classifier: Programming Language :: Python
Classifier: Programming Language :: Python :: 3
Classifier: Programming Language :: Python :: 3.6
Classifier: Programming Language :: Python :: 3.7
Classifier: Programming Language :: Python :: 3.8
Classifier: Programming Language :: Python :: Implementation :: CPython
Classifier: Programming Language :: Python :: Implementation :: PyPy
Requires-Python: >=3.6.0
Provides-Extra: docs
Provides-Extra: test
Provides-Extra: dev
